{
  "slug": "split_tax/37_этой_суммы_нарастающим_итогом_с_начала_года_ведет_к_утрате_права_на_усн_и_переходу.meta.json",
  "title": "{",
  "access": "public",
  "price_from": null,
  "path": "data/docs/split_tax/37_этой_суммы_нарастающим_итогом_с_начала_года_ведет_к_утрате_права_на_усн_и_переходу.meta.json",
  "content": "{\n  \"title\": \"этой суммы (нарастающим итогом с начала года) ведет к утрате права на УСН и переходу\",\n  \"slug\": \"этой_суммы_нарастающим_итогом_с_начала_года_ведет_к_утрате_права_на_усн_и_переходу\",\n  \"source\": \"02_tax_regimes_crimea_2026_ru.txt\",\n  \"index\": 37,\n  \"language\": \"ru\"\n}"
}